imagepypelines_tools/__init__.py
imagepypelines_tools/imagepypelines_tools.py
imagepypelines_tools/version_info.py
imagepypelines_tools/dockerfiles/imagepypelines-base.Dockerfile
imagepypelines_tools/dockerfiles/imagepypelines-gpu.Dockerfile
imagepypelines_tools/dockerfiles/startup.sh
imagepypelines_tools-0.4.0a0.dist-info/LICENSE
imagepypelines_tools-0.4.0a0.dist-info/METADATA
imagepypelines_tools-0.4.0a0.dist-info/WHEEL
imagepypelines_tools-0.4.0a0.dist-info/entry_points.txt
imagepypelines_tools-0.4.0a0.dist-info/top_level.txt
imagepypelines_tools-0.4.0a0.dist-info/RECORD
