Metadata-Version: 2.1
Name: imagepypelines-tools
Version: 0.4.0a0
Summary: accessory library to augment the image processing library imagepypelines
Home-page: https://www.imagepypelines.org
Author: Jeff Maggio, Nathan Dileas, Ryan Hartzell
Author-email: jmaggio14@gmail.com
Maintainer: Jeff Maggio
Maintainer-email: jmaggio14@gmail.com
License: MIT
Download-URL: https://github.com/jmaggio14/imagepypelines-tools
Keywords: imaging-science machine-learning computer-vision data-pipelines docker
Platform: Windows
Platform: Linux
Platform: Mac OS-X
Platform: Unix
Classifier: Development Status :: 3 - Alpha
Classifier: Intended Audience :: Science/Research
Classifier: Topic :: Scientific/Engineering :: Artificial Intelligence
Classifier: Topic :: Scientific/Engineering :: Image Recognition
Classifier: Topic :: Scientific/Engineering :: Information Analysis
Classifier: License :: OSI Approved :: MIT License
Classifier: Programming Language :: Python
Classifier: Programming Language :: Python :: 3
Classifier: Programming Language :: Python :: 3.4
Classifier: Programming Language :: Python :: 3.5
Classifier: Programming Language :: Python :: 3.6
Classifier: Programming Language :: Python :: Implementation :: CPython
Classifier: Operating System :: MacOS :: MacOS X
Classifier: Operating System :: Microsoft :: Windows
Classifier: Operating System :: POSIX
Classifier: Natural Language :: English
Requires-Python: >=3.4.*,!=3.7.*
